contextcol_binance_spot_sdk/__init__.py
contextcol_binance_spot_sdk/binance_account.py
contextcol_binance_spot_sdk/binance_client.py
contextcol_binance_spot_sdk/binance_market_data.py
contextcol_binance_spot_sdk/binance_trading.py
contextcol_binance_spot_sdk/client.py
contextcol_binance_spot_sdk/config.py
contextcol_binance_spot_sdk/contextcol_api.py
contextcol_binance_spot_sdk/exceptions.py
contextcol_binance_spot_sdk-0.1.11.dist-info/LICENSE
contextcol_binance_spot_sdk-0.1.11.dist-info/METADATA
contextcol_binance_spot_sdk-0.1.11.dist-info/WHEEL
contextcol_binance_spot_sdk-0.1.11.dist-info/RECORD
