Metadata-Version: 2.3
Name: contextcol-binance-spot-sdk
Version: 0.1.11
Summary: Python SDK for Binance trading with ContextCol API integration
Keywords: binance,trading,api,contextcol,cryptocurrency,binance,spot
Author: khemmapich
Author-email: khemmapich@contextcol.com
Requires-Python: >=3.9,<4.0
Classifier: Development Status :: 3 - Alpha
Classifier: Intended Audience :: Developers
Classifier: License :: OSI Approved :: MIT License
Classifier: Programming Language :: Python :: 3
Classifier: Programming Language :: Python :: 3.9
Classifier: Programming Language :: Python :: 3.10
Classifier: Programming Language :: Python :: 3.11
Classifier: Programming Language :: Python :: 3.12
Classifier: Programming Language :: Python :: 3.13
Classifier: Programming Language :: Python :: 3.8
Classifier: Topic :: Office/Business :: Financial
Classifier: Topic :: Software Development :: Libraries :: Python Modules
Requires-Dist: cryptography (>=3.4.8,<4.0.0)
Requires-Dist: docutils (>=0.21.2,<0.22.0)
Requires-Dist: dotenv (>=0.9.9,<0.10.0)
Requires-Dist: loguru (>=0.7.2,<0.8.0)
Requires-Dist: pydantic (>=2.0.0,<3.0.0)
Requires-Dist: python-dotenv (>=1.0.0,<2.0.0)
Requires-Dist: requests (>=2.28.0,<3.0.0)
Project-URL: Bug Tracker, https://github.com/khemmapichpanyana/contextcol-binance-spot-sdk/issues
Project-URL: Documentation, https://github.com/khemmapichpanyana/contextcol-binance-spot-sdk
Project-URL: Homepage, https://github.com/khemmapichpanyana/contextcol-binance-spot-sdk
Project-URL: Repository, https://github.com/khemmapichpanyana/contextcol-binance-spot-sdk
